pytest_github_actions_annotate_failures/__init__.py
pytest_github_actions_annotate_failures/plugin.py
pytest_github_actions_annotate_failures-0.3.0.dist-info/LICENSE
pytest_github_actions_annotate_failures-0.3.0.dist-info/METADATA
pytest_github_actions_annotate_failures-0.3.0.dist-info/WHEEL
pytest_github_actions_annotate_failures-0.3.0.dist-info/entry_points.txt
pytest_github_actions_annotate_failures-0.3.0.dist-info/top_level.txt
pytest_github_actions_annotate_failures-0.3.0.dist-info/RECORD
