Metadata-Version: 2.2
Name: pytest-github-actions-annotate-failures
Version: 0.3.0
Summary: pytest plugin to annotate failed tests with a workflow command for GitHub Actions
Author-email: utgwkk <utagawakiki@gmail.com>
Maintainer-email: utgwkk <utagawakiki@gmail.com>
License: MIT
Project-URL: homepage, https://github.com/pytest-dev/pytest-github-actions-annotate-failures
Project-URL: repository, https://github.com/pytest-dev/pytest-github-actions-annotate-failures
Project-URL: changelog, https://github.com/pytest-dev/pytest-github-actions-annotate-failures/releases
Keywords: ansible,testing,molecule,plugin
Classifier: Development Status :: 5 - Production/Stable
Classifier: Environment :: Console
Classifier: Intended Audience :: Developers
Classifier: Intended Audience :: Information Technology
Classifier: Intended Audience :: System Administrators
Classifier: License :: OSI Approved :: MIT License
Classifier: Framework :: Pytest
Classifier: Programming Language :: Python :: 3
Classifier: Programming Language :: Python :: 3.8
Classifier: Programming Language :: Python :: 3.9
Classifier: Programming Language :: Python :: 3.10
Classifier: Programming Language :: Python :: 3.11
Classifier: Programming Language :: Python :: 3.12
Classifier: Programming Language :: Python :: 3.13
Classifier: Programming Language :: Python :: 3 :: Only
Classifier: Programming Language :: Python
Classifier: Topic :: System :: Systems Administration
Classifier: Topic :: Software Development :: Quality Assurance
Classifier: Topic :: Software Development :: Testing
Classifier: Topic :: Utilities
Requires-Python: >=3.8
License-File: LICENSE
Requires-Dist: pytest>=6.0.0
